{
  "$schema": "https://developer.microsoft.com/json-schemas/fabric/item/report/definition/visualContainer/2.5.0/schema.json",
  "name": "7a9b31ce6f2649f6a412",
  "position": {
    "x": 0,
    "y": 0,
    "z": 0,
    "height": 720,
    "width": 204,
    "tabOrder": 0
  },
  "visual": {
    "visualType": "shape",
    "objects": {
      "shape": [
        {
          "properties": {
            "tileShape": {
              "expr": {
                "Literal": {
                  "Value": "'rectangle'"
                }
              }
            }
          }
        }
      ],
      "rotation": [
        {
          "properties": {
            "shapeAngle": {
              "expr": {
                "Literal": {
                  "Value": "0L"
                }
              }
            }
          }
        }
      ]
    },
    "drillFilterOtherVisuals": true
  },
  "howCreated": "InsertVisualButton"
}